hocc.v
module hockey(

    input clk,
    input rst,
    
    input BTNA,
    input BTNB,
    
    input [1:0] DIRA,
    input [1:0] DIRB,
    
    input [2:0] YA,
    input [2:0] YB,
   
    output reg [2:0] X_COORD,
	output reg [2:0] Y_COORD
    );

    reg [3:0] cstate; //current state
    reg [3:0] nstate; //next state

    parameter [7:0] s0 = 8'b00000000; //IDLE
    parameter [7:0] s1 = 8'b00000001; //BTNA == 1
    parameter [7:0] s2 = 8'b00000010; //BTNB == 1
    parameter [7:0] s3 = 8'b00000011; //send to B from A //no timer
    parameter [7:0] s4 = 8'b00000100; //send to A from B //no timer
    parameter [7:0] s5 = 8'b00000101; // win state stays here forever until rst = 1
    parameter [7:0] s6 = 8'b00000110; // Display
    parameter [7:0] s7 = 8'b00000111; // respond B
    parameter [7:0] s8 = 8'b00001000; // respond A
    parameter [7:0] s9 = 8'b00001001; // goal_B
    parameter [7:0] s10 = 8'b00001010; // goal_A

   
    
    parameter [6:0] DIGIT_0 = 7'b0000001; // Example pattern for digit 0
    parameter [6:0] DIGIT_1 = 7'b1001111; // Example pattern for digit 1
    parameter [6:0] DIGIT_2 = 7'b0010010; // Example pattern for digit 2
    parameter [6:0] DIGIT_3 = 7'b0000110; // Example pattern for digit 3


    parameter LD_NONE = 5'b00000;
    parameter LD_ALL = 5'b11111;
    parameter LD_0 = 5'b00001;
    parameter LD_1 = 5'b00010;
    parameter LD_2 = 5'b00100;
    parameter LD_3 = 5'b01000;
    parameter LD_4 = 5'b10000;


    
    //else yaz
    //ID: 29015 / 27968;

    reg btn_A;
    reg btn_B;

    reg x1;
    reg [3:0] y1;

    reg [2:0] guess_y_A;
    reg [2:0] guess_y_B;
    reg [1:0] turn = 2; // 0 = A , 1 = B, 2 = standby
    reg [1:0] score_A;
    reg [1:0] score_B;
    reg [1:0] win;
    reg [7:0] timer;
    reg[1:0] correct_guess_B;
    reg[1:0] correct_guess_A;




        always @(posedge clk or posedge rst)
        begin
            
        
            if(rst == 1)begin
                cstate <= s0;
                X_COORD <= 3'b000;
                Y_COORD <= 3'b000;
                score_A <= 2'b00;
                score_B <= 2'b00;
                btn_A <= 1'b0;
                btn_B <= 1'b0;
                win <= 0;
                timer <= 0;
                correct_guess_B <= 0;
                correct_guess_A <= 0;
            
            end
            else begin
                cstate <= nstate;
           

            if(cstate == s0)begin
                if(BTNA == 1 && BTNB == 0)begin
                    turn <= 0;
                end

                else if(BTNB == 1 && BTNA == 0)begin
                    turn <= 1;
                end
                else if(BTNB == 0 && BTNA == 0 && turn == 2) begin
                    turn <= 2;
                end
                else if(BTNB == 1 && BTNA == 1 && turn == 2) begin
                    turn <= 2;
                end

            end

            else if(cstate == s1)begin
                timer <= 0;
                if(BTNA == 1)begin
                Y_COORD <= YA;
                y1 <= DIRA;
                btn_A <= 1;
                X_COORD <= 0;
                end;

            
                
            end
            else if(cstate == s2)begin
                timer <= 0;

                
                if(BTNB == 1) begin
                Y_COORD <= YB;
                y1 <= DIRB;
                btn_B <= 1;
                X_COORD <= 4;
                end
               
                
            end
            
            else if(cstate == s3)begin
                
                //win state check code from here
                /*if( score_B >= 3)begin
                    win <= win + 1;
                end
                if( score_A >= 3)begin
                    win <= win + 1;
                end*/
                //to here

                correct_guess_A <= 0;

                if(timer < 2)begin
                    
                    timer <= timer + 1;
                end
                else begin

                    timer <= 0;
                    if(X_COORD < 3'b100)begin
                        X_COORD <= X_COORD + 1;
                        guess_y_B <= YB;
                        if(BTNB == 1)begin
                        btn_B <= 1;
                    end
                    
                end
                if(X_COORD == 3'b100)begin
                    guess_y_B <= YB;
                    turn <= 1;
                    if(BTNB == 1)begin
                        btn_B <= 1;
                    end
                    if(BTNB == 0)begin
                        btn_B <= 0;
                    end
                    
                    /*if((guess_y_B != Y_COORD) | (btn_B == 0))begin
                        score_A <= score_A + 1;
                    end
                    if((guess_y_B == Y_COORD) | (btn_B == 0))begin
                        Y_COORD <= Y_COORD;
                    end*/
    
                end

                    if ( y1 == 2'd1)begin 
                        if (Y_COORD < 3'b100)begin
                            Y_COORD[0] <= 1 ^ Y_COORD[0];
                            Y_COORD[1] <= Y_COORD[0] ^ Y_COORD[1];
                            Y_COORD[2] <= ((Y_COORD[0] & Y_COORD[1]) ^ Y_COORD[2]);
                            y1 <= 2'd1; 
                            end
                        else if(Y_COORD == 3'b100)begin
                            y1 <= 2'd2;
                            Y_COORD <= 3'b100;
                            end
                    end
                    if (y1 == 2'd2)begin
                        if ( Y_COORD > 3'b000)begin

                                    Y_COORD[0] <= (1 ^ Y_COORD[0]);
                                    Y_COORD[1] <= ((~Y_COORD[0]) ^ Y_COORD[1] );
                                    Y_COORD[2] <= Y_COORD[2] ^ Y_COORD[2];
                                    y1 <= 2'd2;
                                end
                        else if (Y_COORD == 3'b000 )begin
                                y1 <= 2'd1;
                                Y_COORD <= 3'b000;
                            end
                    end
                    if (y1 == 2'd0)begin
                        Y_COORD <= Y_COORD;
                    end
                end

                end

            else if(cstate == s4)begin
                
                //win state check code from here
               /* if( score_B >= 3)begin
                    win <= win + 1;
                end
                if( score_A >= 3)begin
                    win <= win + 1;
                end*/
                //to here

                correct_guess_B <= 0;


                if(timer < 2)begin
                    timer <= timer + 1;
                end
                
                else begin
                    timer <= 0;
                    if(X_COORD > 3'b000)begin
                        X_COORD <= (X_COORD - 1);
                        guess_y_A <= YA;
                        if(BTNA == 1)begin
                            btn_A <= 1;
                        end
                        if(BTNA == 0)begin
                            btn_A <= 0;
                        end
                    end

                    if(X_COORD == 3'b000)begin
                        guess_y_A <= YA;
                        turn <= 0;
                        if(BTNA == 1)begin
                            btn_A <= 1;
                        end
                        if(BTNA == 0)begin
                            btn_A <= 0;
                        end
                        
                        /*if((guess_y_A != Y_COORD) | (btn_A == 0))begin
                            score_B <= score_B + 1;
                        end
                        if((guess_y_A == Y_COORD) | (btn_A == 0))begin
                            Y_COORD <= Y_COORD;
                        end*/
                    
                    end
                
                    if ( y1 == 2'd1)begin 
                        if (Y_COORD < 3'b100)begin
                            Y_COORD[0] <= 1 ^ Y_COORD[0];
                            Y_COORD[1] <= Y_COORD[0] ^ Y_COORD[1];
                            Y_COORD[2] <= ((Y_COORD[0] & Y_COORD[1]) ^ Y_COORD[2]);
                            y1 <= 2'd1; 
                            end
                        else if(Y_COORD == 3'b100)begin
                            y1 <= 2'd2;
                            Y_COORD <= 3'b100;
                            end
                    end
               
                    if (y1 == 2'd2)begin
                        if ( Y_COORD > 3'b000)begin                
                                Y_COORD[0] <= (1 ^ Y_COORD[0]);
                                Y_COORD[1] <= ((~Y_COORD[0]) ^ Y_COORD[1] );
                                Y_COORD[2] <= Y_COORD[2] ^ Y_COORD[2];
                                y1 <= 2'd2;
                            end
                    else if (Y_COORD == 3'b000 )begin
                            y1 <= 2'd1;
                            Y_COORD <= 3'b000;
                        end
                end
                
                    if (y1 == 2'd0)begin
                        Y_COORD <= Y_COORD;
                    end
                end
            end

            else if( cstate == s6)begin
                timer <= timer + 1;
            end

            
            else if( cstate == s7)begin

                if(timer < 2 )begin
            
                    /*if(BTNA == 1)begin
                        guess_y_B <= YB;
                    end*/

                    guess_y_B <= YB;
                    timer <= timer + 1;
                    
                    if((guess_y_B != Y_COORD) && (BTNB == 1))begin
                        correct_guess_B <= 0;
                        score_A <= score_A + 1;
                        //turn <= 1;
                    end

                    else if((guess_y_B == Y_COORD) && (BTNB == 1))begin
                        correct_guess_B <= 1;
                        X_COORD <= 3;
                        //turn <= 1;
                    end

                    else begin
                        correct_guess_B <= 0;
                        score_A <= score_A + 1;
                    end
                end

                else begin
                    correct_guess_B <= 0;
                    score_A <= score_A + 1;
                    timer <= 0;
                end
                    

                
                    
                
            end

            else if( cstate == s9)begin
                timer <= timer + 1;
            end

            else if( cstate == s8)begin
                if(timer < 2 )begin
                    
                    guess_y_A <= YA;
                    timer <= timer + 1; 
                    

                    if((guess_y_A != Y_COORD) && (BTNA == 1))begin
                        correct_guess_A <= 0;
                        score_B <= score_B + 1;
                    end

                    else if((guess_y_A == Y_COORD) && (BTNA == 1))begin
                        correct_guess_A <= 1;
                        X_COORD <= 1;
                        
                    end
                    
                    else begin
                        correct_guess_A <= 0;
                        score_B <= score_B + 1;
                    end

                end

                else begin
                    correct_guess_A <= 0;
                    score_B <= score_B + 1;
                    timer <= 0;
                end
            end
                    
            
        end

        
        
    
           
        end

/*
        always@(*)
        begin

            if(cstate == s0)begin
                if(BTNA == 1 && BTNB == 0)begin
                    turn = 0;
                end

                else if(BTNB == 1 && BTNA == 0)begin
                    turn = 1;
                end
                else if(BTNB == 0 && BTNA == 0) begin
                    turn = 2;
                end
                else if(BTNB == 1 && BTNA == 1) begin
                    turn = 2;
                end
                else begin
                    turn = 2;
                end
            end
        end
       */




        always @(*)
        begin

            case(cstate)

                s0:
                begin
                    /*if(rst == 1)begin
                        X_COORD = 3'b000;
                        Y_COORD = 3'b000;
                        score_A = 2'b00;
                        score_B = 2'b00;
                        btn_A = 1'b0;
                        btn_B = 1'b0;
                        turn  = 2;
                        win = 0;
                        timer = 0;
                        correct_guess_B = 0;
                        correct_guess_A = 0;
                    end
                    else begin
                        ; //do nothing
                    end*/
                    
                    //x1 <= 1'b0;
                    //btn_A <= BTNA;
                    //btn_B <= BTNB;

                    if(turn == 0)begin
                        nstate = s6;
                        //turn = 0;
                    end

                    else if(turn == 1)begin
                        nstate = s6;
                        //turn = 1;
                    end
                    else if(turn == 2) begin
                        nstate = s0;
                    end
                    else if(turn == 2) begin
                        nstate = s0;
                    end

                    else begin
                        nstate = s0;
                    end
                    
                end


                
                s1:
                begin
                        if((YA < 3'b101 ) && (BTNA == 1'b1))begin
                            nstate = s3;
                            //y1 = DIRA;
                        end
                        else begin
                            nstate = s1;
                        end

                        
                end

                s2:
                begin
                        if( (YB < 5 ) && (BTNB == 1'b1))begin
                            nstate = s4;
                            //y1 = DIRB;
                            
                        end
                        else begin
                            nstate = s2;
                        end
                end

                s3:
                begin    

                        if (X_COORD < 3'b100)begin
                            nstate = s3;
                            //#5; //speed of the puck
                        end
                        else if(X_COORD == 3'b100)begin
                            nstate = s7;
                        end
                        else begin
                            nstate = s0;
                        end
                        
                        /*if(win >= 1)begin
                            nstate = s5;
                        end*/
                end

                s4:
                begin
                    
                        if (X_COORD > 3'b000)begin
                            nstate = s4;
                            //#5; //speed of the puck
                        end
                        else if(X_COORD == 3'b000)begin
                            nstate = s8; //s1
                        end
                        else begin
                            nstate = s0;
                        end
                        
                        /*if(win >= 1)begin
                            nstate = s5;
                        end*/
                end

                s5:
                begin
                    // win state stays here forever until rst = 1;
                    nstate = s5;
                end

                s6: // DISP
                begin
                
                    if(turn == 0)begin
                        if (timer >= 2) begin
                        nstate = s1;
                        //turn = 0;
                        end

                        else begin
                            nstate = s6;
                        end

                        
                    end

                    else begin
                        if (timer >= 2)begin
                        nstate = s2;
                        //turn = 1;
                        end

                        else begin
                            nstate = s6;
                        end


                    end
                end
                s7:
                begin
                    
                    if(timer >= 2)begin
                        if(correct_guess_B == 1 ) begin
                            nstate = s4;
                        end

                        else begin
                            nstate = s9;
                        end
                    end
                    else begin
                        nstate <= s7;
                    end
 
                end

                s9:
                begin
                    if(timer <= 2)begin
                        nstate = s9;
                    end
                    else begin
                        if(score_A == 3)begin
                        nstate = s5;
                        end
                        else begin
                            nstate = s2;
                        end
                    end
                end

                s8:
                begin

                    if(timer >= 2)begin
                        if(correct_guess_A == 1 ) begin
                            nstate = s3;
                        end

                        else begin
                            nstate = s10;
                        end
                    end
                    else begin
                        nstate = s8;
                    end
 
                end

                s10:
                begin
                    if(timer < 2)begin
                        nstate = s10;
                    end
                    else begin
                        if(score_B == 3)begin
                        nstate = s5;
                        end
                        else begin
                            nstate = s1;
                        end
                    end
                end


                
                

            endcase
        
        end

 




endmodule

hockey_tb.v
module hockey_tb();


parameter HP = 5;       // Half period of our clock signal
parameter FP = (2*HP);  // Full period of our clock signal

reg clk, rst, BTNA, BTNB;
reg [1:0] DIRA;
reg [1:0] DIRB;
reg [2:0] YA;
reg [2:0] YB;

wire [2:0] X_COORD, Y_COORD;

// Our design-under-test is the DigiHockey module
hockey dut(clk, rst, BTNA, BTNB, DIRA, DIRB, YA, YB, X_COORD,Y_COORD);

// This always statement automatically cycles between clock high and clock low in HP (Half Period) time. Makes writing test-benches easier.
always #HP clk = ~clk;

initial begin
    $dumpfile("hockey.vcd"); //  * Our waveform is saved under this file.
    $dumpvars(0,hockey_tb); // * Get the variables from the module.
    
    $display("Simulation started.");

    clk = 0; 
    rst = 0;
    BTNA = 0;
	BTNB = 0;
	DIRA = 0;
	DIRB = 0;
    YA = 0;
    YB = 0;
    
	#FP; //10
	rst=1;
	#FP; //20
	rst=0;
	// Here, you are asked to write your test scenario.
	
	//BTNB = 1;
	#FP; //30

	#FP; //40
	#FP; //50
	#FP; //60
	
	BTNB = 0;
	BTNA = 1;
	#FP; //70
	BTNA = 0;
	#FP; //80
	BTNA = 1;
	DIRA = 0;
	YA = 2;
	#FP; //90
	BTNA = 0;
	#FP; //100
	#FP; //110
	YB = 2;
	BTNB = 1;
	#FP; //120
	YB = 2;
	BTNB = 1;
	//BTNB = 1;
	#FP; //130
	BTNA = 0;
	
	//DIRB = 2;
	
	#FP; //140
	BTNA = 1;
	DIRA = 0;
	//BTNB = 0;
	#FP; //160
	BTNA = 0;
	#FP; //170
	#FP; //180
	#FP; //190
	#FP; //200
	#FP; //210
	#FP; //220
	#FP; //230
	#FP; //240
	YB = 2;
	#FP; //250
	YB = 2;
	#FP; //260
	BTNB = 1;
	#FP; //270
	BTNB = 1;
	#FP; //280
	BTNB = 1;
	#FP; //290
	BTNB = 1;
	#FP; //300
	BTNB = 0;
	#FP; //310
	#FP; //320
	DIRB = 0;
	YB = 3;
	BTNB = 1;

	#FP; //330
	BTNB = 0;
	#FP; //340
	#FP; //350
	#FP; //360
	#FP; //370
	#FP; //380
	#FP; //390
	#FP; //400
	#FP; //410
	#FP; //420
	#FP; //430
	#FP; //440
	#FP; //450
	#FP; //460
	#FP; //470




	
	
	
	
	
	
	
	$display("Simulation finished.");
    $finish(); // Finish simulation.
	
end



endmodule

hockey.vcd
$date
	Sun Jan 07 12:47:57 2024
$end
$version
	Icarus Verilog
$end
$timescale
	1s
$end
$scope module hockey_tb $end
$var wire 3 ! Y_COORD [2:0] $end
$var wire 3 " X_COORD [2:0] $end
$var parameter 64 # FP $end
$var parameter 32 $ HP $end
$var reg 1 % BTNA $end
$var reg 1 & BTNB $end
$var reg 2 ' DIRA [1:0] $end
$var reg 2 ( DIRB [1:0] $end
$var reg 3 ) YA [2:0] $end
$var reg 3 * YB [2:0] $end
$var reg 1 + clk $end
$var reg 1 , rst $end
$scope module dut $end
$var wire 1 % BTNA $end
$var wire 1 & BTNB $end
$var wire 2 - DIRA [1:0] $end
$var wire 2 . DIRB [1:0] $end
$var wire 3 / YA [2:0] $end
$var wire 3 0 YB [2:0] $end
$var wire 1 + clk $end
$var wire 1 , rst $end
$var parameter 7 1 DIGIT_0 $end
$var parameter 7 2 DIGIT_1 $end
$var parameter 7 3 DIGIT_2 $end
$var parameter 7 4 DIGIT_3 $end
$var parameter 5 5 LD_0 $end
$var parameter 5 6 LD_1 $end
$var parameter 5 7 LD_2 $end
$var parameter 5 8 LD_3 $end
$var parameter 5 9 LD_4 $end
$var parameter 5 : LD_ALL $end
$var parameter 5 ; LD_NONE $end
$var parameter 8 < s0 $end
$var parameter 8 = s1 $end
$var parameter 8 > s10 $end
$var parameter 8 ? s2 $end
$var parameter 8 @ s3 $end
$var parameter 8 A s4 $end
$var parameter 8 B s5 $end
$var parameter 8 C s6 $end
$var parameter 8 D s7 $end
$var parameter 8 E s8 $end
$var parameter 8 F s9 $end
$var reg 3 G X_COORD [2:0] $end
$var reg 3 H Y_COORD [2:0] $end
$var reg 1 I btn_A $end
$var reg 1 J btn_B $end
$var reg 2 K correct_guess_A [1:0] $end
$var reg 2 L correct_guess_B [1:0] $end
$var reg 4 M cstate [3:0] $end
$var reg 3 N guess_y_A [2:0] $end
$var reg 3 O guess_y_B [2:0] $end
$var reg 4 P nstate [3:0] $end
$var reg 2 Q score_A [1:0] $end
$var reg 2 R score_B [1:0] $end
$var reg 8 S timer [7:0] $end
$var reg 2 T turn [1:0] $end
$var reg 2 U win [1:0] $end
$var reg 4 V y1 [3:0] $end
$upscope $end
$upscope $end
$enddefinitions $end
$comment Show the parameter values. $end
$dumpall
b1001 F
b1000 E
b111 D
b110 C
b101 B
b100 A
b11 @
b10 ?
b1010 >
b1 =
b0 <
b0 ;
b11111 :
b10000 9
b1000 8
b100 7
b10 6
b1 5
b110 4
b10010 3
b1001111 2
b1 1
b101 $
b1010 #
$end
#0
$dumpvars
bx V
bx U
b10 T
bx S
bx R
bx Q
bx P
bx O
bx N
bx M
bx L
bx K
xJ
xI
bx H
bx G
b0 0
b0 /
b0 .
b0 -
0,
0+
b0 *
b0 )
b0 (
b0 '
0&
0%
bx "
bx !
$end
#5
1+
#10
b0 P
b0 K
b0 L
b0 S
b0 U
0J
0I
b0 R
b0 Q
b0 !
b0 H
b0 "
b0 G
b0 M
0+
1,
#15
1+
#20
0+
0,
#25
1+
#30
0+
#35
1+
#40
0+
#45
1+
#50
0+
#55
1+
#60
0+
1%
#65
b110 P
b0 T
1+
#70
0+
0%
#75
b110 M
1+
#80
0+
b10 )
b10 /
1%
#85
b1 S
1+
#90
0+
0%
#95
b1 P
b10 S
1+
#100
0+
#105
b11 S
b1 M
1+
#110
0+
1&
b10 *
b10 0
#115
b0 S
1+
#120
0+
#125
1+
#130
0+
#135
1+
#140
b11 P
0+
1%
#145
1I
b0 V
b10 !
b10 H
b11 M
1+
#150
0+
0%
#155
b1 S
1+
#160
0+
#165
b10 S
1+
#170
0+
#175
1J
b10 O
b1 "
b1 G
b0 S
1+
#180
0+
#185
b1 S
1+
#190
0+
#195
b10 S
1+
#200
0+
#205
b10 "
b10 G
b0 S
1+
#210
0+
#215
b1 S
1+
#220
0+
#225
b10 S
1+
#230
0+
#235
b11 "
b11 G
b0 S
1+
#240
0+
#245
b1 S
1+
#250
0+
#255
b10 S
1+
#260
0+
#265
b111 P
b100 "
b100 G
b0 S
1+
#270
0+
#275
b1 S
b111 M
1+
#280
0+
#285
b100 P
b11 "
b11 G
b1 L
b10 S
1+
#290
0+
0&
#295
b0 S
b1 Q
b0 L
b100 M
1+
#300
0+
#305
b1 S
1+
#310
0+
1&
b11 *
b11 0
#315
b10 S
1+
#320
0+
0&
#325
0I
b10 N
b10 "
b10 G
b0 S
1+
#330
0+
#335
b1 S
1+
#340
0+
#345
b10 S
1+
#350
0+
#355
b1 "
b1 G
b0 S
1+
#360
0+
#365
b1 S
1+
#370
0+
#375
b10 S
1+
#380
0+
#385
b1000 P
b0 "
b0 G
b0 S
1+
#390
0+
#395
b1 S
b1000 M
1+
#400
0+
#405
b1010 P
b1 R
b10 S
1+
#410
0+
#415
b0 S
b10 R
b1010 M
1+
